pixelate_redactor/__init__.py
pixelate_redactor/pixelate_redactor.py
pixelate_redactor-0.4.data/scripts/pixelate-redactor
pixelate_redactor-0.4.data/scripts/pixelate-redactor-boxes
pixelate_redactor-0.4.dist-info/METADATA
pixelate_redactor-0.4.dist-info/RECORD
pixelate_redactor-0.4.dist-info/WHEEL
pixelate_redactor-0.4.dist-info/top_level.txt
