Metadata-Version: 2.1
Name: pixelate-redactor
Version: 0.4
Summary: Library that provides pixelation for image redaction
Home-page: https://github.com/Eradash/pixelate-redactor
Author: Vincent Poirier
Author-email: vincent.poirier@tlmgo.com
License: BSD
Platform: UNKNOWN
Classifier: Environment :: Console
Classifier: Intended Audience :: Developers
Classifier: License :: OSI Approved :: BSD License
Classifier: Programming Language :: Python :: 2.6
Classifier: Programming Language :: Python :: 2.7
Classifier: Programming Language :: Python :: 3
Classifier: Programming Language :: Python :: 3.2
Classifier: Programming Language :: Python :: 3.3
Classifier: Programming Language :: Python :: 3.4
Classifier: Programming Language :: Python :: 3.5
Classifier: Programming Language :: Python :: 3.6
Classifier: Programming Language :: Python :: 3.7
Requires: pillow
